arepytools/__init__.py
arepytools/_utils.py
arepytools/constants.py
arepytools/geometry/__init__.py
arepytools/geometry/_ellipsoid.py
arepytools/geometry/_interpolator.py
arepytools/geometry/conversions.py
arepytools/geometry/generalsarattitude.py
arepytools/geometry/generalsarorbit.py
arepytools/geometry/wgs84.py
arepytools/geometry/_geocoding/__init__.py
arepytools/geometry/_geocoding/_direct_geocoding.py
arepytools/geometry/_geocoding/_inverse_geocoding.py
arepytools/geometry/_geocoding/_newton.py
arepytools/io/__init__.py
arepytools/io/_utils.py
arepytools/io/channel.py
arepytools/io/debugio.py
arepytools/io/metadata.py
arepytools/io/productfolder.py
arepytools/io/parsing/__init__.py
arepytools/io/parsing/pyxb_aresys_conversion.py
arepytools/io/parsing/pyxb_metadata.py
arepytools/io/parsing/pyxb_metadata_types.py
arepytools/math/__init__.py
arepytools/math/axis.py
arepytools/math/genericpoly.py
arepytools/timing/__init__.py
arepytools/timing/precisedatetime.py
biopal/__init__.py
biopal/__main__.py
biopal/_package_data/conf/Configuration_File.xml
biopal/_package_data/inputs/Input_File.xml
biopal/agb/__init__.py
biopal/agb/estimating_AGB.py
biopal/agb/main_AGB.py
biopal/agb/processing_AGB.py
biopal/data_operations/__init__.py
biopal/data_operations/data_operations.py
biopal/dataset_query/__init__.py
biopal/dataset_query/dataset_query.py
biopal/fd/__init__.py
biopal/fd/main_FD.py
biopal/fd/processing_FD.py
biopal/fd/tests/__init__.py
biopal/fd/tests/test_fd.py
biopal/fh/__init__.py
biopal/fh/main_FH.py
biopal/fh/processing_FH.py
biopal/fnf/__init__.py
biopal/fnf/main_FNF.py
biopal/fnf/processing_FNF.py
biopal/geocoding/__init__.py
biopal/geocoding/geocoding.py
biopal/geometry/EGM2008.py
biopal/geometry/__init__.py
biopal/geometry/ext_geodata_mosaic.py
biopal/geometry/geometric_lib.py
biopal/geometry/utility_geometry.py
biopal/ground_cancellation/__init__.py
biopal/ground_cancellation/ground_cancellation.py
biopal/ground_cancellation/tests/__init__.py
biopal-0.4.0rc0.dist-info/LICENSE
biopal-0.4.0rc0.dist-info/METADATA
biopal-0.4.0rc0.dist-info/WHEEL
biopal-0.4.0rc0.dist-info/entry_points.txt
biopal-0.4.0rc0.dist-info/top_level.txt
biopal-0.4.0rc0.dist-info/RECORD
