Metadata-Version: 2.1
Name: biopal
Version: 0.4.0rc0
Summary: BIOMASS Product Algorithm Laboratory
Home-page: https://biopal.org/
Author: the BioPAL team
Author-email: biopal@esa.int
License: MIT
Classifier: License :: OSI Approved :: MIT License
Classifier: Operating System :: OS Independent
Classifier: Programming Language :: Python
Classifier: Programming Language :: Python :: 3
Classifier: Programming Language :: Python :: 3 :: Only
Classifier: Programming Language :: Python :: 3.7
Classifier: Programming Language :: Python :: 3.8
Classifier: Programming Language :: Python :: 3.9
Requires-Python: >=3.9
License-File: LICENSE
Requires-Dist: GDAL
Requires-Dist: lxml
Requires-Dist: matplotlib
Requires-Dist: numpy <1.24
Requires-Dist: scipy
Requires-Dist: shapely
Requires-Dist: scikit-image
Requires-Dist: pandas
Requires-Dist: pyproj
Requires-Dist: setuptools ==60.8.2
Requires-Dist: equi7grid ==0.0.11
Requires-Dist: Pytileproj
Requires-Dist: progressbar2
Requires-Dist: namedlist
Requires-Dist: pyxb
Requires-Dist: docopt
Requires-Dist: pytest
